Workbook

Sheet Materias Primas
A1: Despiece Palet Freestanding
A2: Ítem | B2: Elementos | C2: Fierro | D2: Medidas [mm] | H2: Largo [mm] | J2: Cantidad | L2: Rendimiento | N2: Sobrante | O2: Cantidad | P2: Precio Neto | Q2: Costo | S2: Peso [kg] | U2: Superficie | V2: OBS.
D3: A | E3: B | F3: C | G3: esp. | H3: Pieza | I3: Tira | J3: x Unid. | K3: Total | L3: x Tira | N3: x Tira | O3: de Tiras | P3: $/Tira | Q3: x Unidad | S3: [kg/m] | T3: [kg] | U3: [mm²/pieza]
A4: 1 | B4: Poste vertical | C4: Perfil 40x40x2,0 mm. | D4: 40 | E4: 40 | G4: 2 | H4: 1020 | I4: 6000 | J4: 4 | K4: =J4*'Costo Directo'!$B$3 -> 120 | L4: =ROUNDDOWN(I4/H4,0) -> 5 | M4: =ROUNDDOWN((I4-N4)/I4,2) -> 0.85 | N4: =I4-L4*H4 -> 900 | O4: =ROUNDUP(K4/L4,0) -> 24 | P4: =+$C$20*S4*I4/1000 -> 12906 | Q4: =+P4/L4*J4 -> 10324.8 | S4: =ROUND((2*(D4+E4)*G4-4*G4^2)*0.00785,2) -> 2.39 | T4: =S4*H4/1000*J4 -> 9.7512 | U4: =(D4+E4+F4*2)*2*H4*J4 -> 652800
A5: 2 | B5: Riel superior lateral | C5: Perfil 40x40x2,0 mm. | D5: 40 | E5: 40 | G5: 2 | H5: 1070 | I5: 6000 | J5: 2 | K5: =J5*'Costo Directo'!$B$3 -> 60 | L5: =ROUNDDOWN(I5/H5,0) -> 5 | M5: =ROUNDDOWN((I5-N5)/I5,2) -> 0.89 | N5: =I5-L5*H5 -> 650 | O5: =ROUNDUP(K5/L5,0) -> 12 | P5: =+$C$20*S5*I5/1000 -> 12906 | Q5: =+P5/L5*J5 -> 5162.4 | S5: =ROUND((2*(D5+E5)*G5-4*G5^2)*0.00785,2) -> 2.39 | T5: =S5*H5/1000*J5 -> 5.1146 | U5: =(D5+E5+F5*2)*2*H5*J5 -> 342400
A6: 3 | B6: Base frontal | C6: Perfil 40x40x2,0 mm. | D6: 40 | E6: 40 | G6: 2 | H6: 1340 | I6: 6000 | J6: 2 | K6: =J6*'Costo Directo'!$B$3 -> 60 | L6: =ROUNDDOWN(I6/H6,0) -> 4 | M6: =ROUNDDOWN((I6-N6)/I6,2) -> 0.89 | N6: =I6-L6*H6 -> 640 | O6: =ROUNDUP(K6/L6,0) -> 15 | P6: =+$C$20*S6*I6/1000 -> 12906 | Q6: =+P6/L6*J6 -> 6453 | S6: =ROUND((2*(D6+E6)*G6-4*G6^2)*0.00785,2) -> 2.39 | T6: =S6*H6/1000*J6 -> 6.4052 | U6: =(D6+E6+F6*2)*2*H6*J6 -> 428800
A7: 4 | B7: Base lateral | C7: Perfil 40x40x2,0 mm. | D7: 40 | E7: 40 | G7: 2 | H7: 1070 | I7: 6000 | J7: 2 | K7: =J7*'Costo Directo'!$B$3 -> 60 | L7: =ROUNDDOWN(I7/H7,0) -> 5 | M7: =ROUNDDOWN((I7-N7)/I7,2) -> 0.89 | N7: =I7-L7*H7 -> 650 | O7: =ROUNDUP(K7/L7,0) -> 12 | P7: =+$C$20*S7*I7/1000 -> 12906 | Q7: =+P7/L7*J7 -> 5162.4 | S7: =ROUND((2*(D7+E7)*G7-4*G7^2)*0.00785,2) -> 2.39 | T7: =S7*H7/1000*J7 -> 5.1146 | U7: =(D7+E7+F7*2)*2*H7*J7 -> 342400
A8: 5 | B8: Diagonal frontal (corto) | C8: Perfil 40x40x2,0 mm. | D8: 40 | E8: 40 | G8: 2 | H8: 863 | I8: 6000 | J8: 4 | K8: =J8*'Costo Directo'!$B$3 -> 120 | L8: =ROUNDDOWN(I8/H8,0) -> 6 | M8: =ROUNDDOWN((I8-N8)/I8,2) -> 0.86 | N8: =I8-L8*H8 -> 822 | O8: =ROUNDUP(K8/L8,0) -> 20 | P8: =+$C$20*S8*I8/1000 -> 12906 | Q8: =+P8/L8*J8 -> 8604 | S8: =ROUND((2*(D8+E8)*G8-4*G8^2)*0.00785,2) -> 2.39 | T8: =S8*H8/1000*J8 -> 8.25028 | U8: =(D8+E8+F8*2)*2*H8*J8 -> 552320 | V8: Plano: detalle 40x40, elevación 40x20
A9: 6 | B9: Diagonal lateral (largo) | C9: Perfil 40x20x2,0 mm. | D9: 40 | E9: 20 | G9: 2 | H9: 1023 | I9: 6000 | J9: 4 | K9: =J9*'Costo Directo'!$B$3 -> 120 | L9: =ROUNDDOWN(I9/H9,0) -> 5 | M9: =ROUNDDOWN((I9-N9)/I9,2) -> 0.85 | N9: =I9-L9*H9 -> 885 | O9: =ROUNDUP(K9/L9,0) -> 24 | P9: =+$C$20*S9*I9/1000 -> 9504 | Q9: =+P9/L9*J9 -> 7603.2 | S9: =ROUND((2*(D9+E9)*G9-4*G9^2)*0.00785,2) -> 1.76 | T9: =S9*H9/1000*J9 -> 7.20192 | U9: =(D9+E9+F9*2)*2*H9*J9 -> 491040 | V9: Plano: detalle 40x20, elevación 40x40
A10: 7 | B10: Diagonal base larga | C10: Perfil 40x40x2,0 mm. | D10: 40 | E10: 40 | G10: 2 | H10: 1578 | I10: 6000 | J10: 1 | K10: =J10*'Costo Directo'!$B$3 -> 30 | L10: =ROUNDDOWN(I10/H10,0) -> 3 | M10: =ROUNDDOWN((I10-N10)/I10,2) -> 0.78 | N10: =I10-L10*H10 -> 1266 | O10: =ROUNDUP(K10/L10,0) -> 10 | P10: =+$C$20*S10*I10/1000 -> 12906 | Q10: =+P10/L10*J10 -> 4302 | S10: =ROUND((2*(D10+E10)*G10-4*G10^2)*0.00785,2) -> 2.39 | T10: =S10*H10/1000*J10 -> 3.77142 | U10: =(D10+E10+F10*2)*2*H10*J10 -> 252480
A11: 8 | B11: Diagonal base corta | C11: Perfil 40x40x2,0 mm. | D11: 40 | E11: 40 | G11: 2 | H11: 766 | I11: 6000 | J11: 2 | K11: =J11*'Costo Directo'!$B$3 -> 60 | L11: =ROUNDDOWN(I11/H11,0) -> 7 | M11: =ROUNDDOWN((I11-N11)/I11,2) -> 0.89 | N11: =I11-L11*H11 -> 638 | O11: =ROUNDUP(K11/L11,0) -> 9 | P11: =+$C$20*S11*I11/1000 -> 12906 | Q11: =+P11/L11*J11 -> 3687.4286 | S11: =ROUND((2*(D11+E11)*G11-4*G11^2)*0.00785,2) -> 2.39 | T11: =S11*H11/1000*J11 -> 3.66148 | U11: =(D11+E11+F11*2)*2*H11*J11 -> 245120
A12: 9 | B12: Soporte ruedas | C12: Perfil 40x40x2,0 mm. | D12: 40 | E12: 40 | G12: 2 | H12: 215 | I12: 6000 | J12: 4 | K12: =J12*'Costo Directo'!$B$3 -> 120 | L12: =ROUNDDOWN(I12/H12,0) -> 27 | M12: =ROUNDDOWN((I12-N12)/I12,2) -> 0.96 | N12: =I12-L12*H12 -> 195 | O12: =ROUNDUP(K12/L12,0) -> 5 | P12: =+$C$20*S12*I12/1000 -> 12906 | Q12: =+P12/L12*J12 -> 1912 | S12: =ROUND((2*(D12+E12)*G12-4*G12^2)*0.00785,2) -> 2.39 | T12: =S12*H12/1000*J12 -> 2.0554 | U12: =(D12+E12+F12*2)*2*H12*J12 -> 137600 | V12: Plano dice L=2015; se usó 215
A13: 10 | B13: Soporte rueda | C13: Perfil 50x50x5,0 mm. | D13: 50 | E13: 50 | G13: 5 | H13: 100 | I13: 6000 | J13: 4 | K13: =J13*'Costo Directo'!$B$3 -> 120 | L13: =ROUNDDOWN(I13/H13,0) -> 60 | M13: =ROUNDDOWN((I13-N13)/I13,2) -> 1 | N13: =I13-L13*H13 -> 0 | O13: =ROUNDUP(K13/L13,0) -> 2 | P13: =+$C$20*S13*I13/1000 -> 38178 | Q13: =+P13/L13*J13 -> 2545.2 | S13: =ROUND((2*(D13+E13)*G13-4*G13^2)*0.00785,2) -> 7.07 | T13: =S13*H13/1000*J13 -> 2.828 | U13: =(D13+E13+F13*2)*2*H13*J13 -> 80000 | V13: Reemplaza perfil 60x60x5,0
A14: 11 | B14: Tapa soporte rueda | C14: Pletina 50x5,0 mm. | D14: 50 | G14: 5 | H14: 50 | I14: 6000 | J14: 4 | K14: =J14*'Costo Directo'!$B$3 -> 120 | L14: =ROUNDDOWN(I14/H14,0) -> 120 | M14: =ROUNDDOWN((I14-N14)/I14,2) -> 1 | N14: =I14-L14*H14 -> 0 | O14: =ROUNDUP(K14/L14,0) -> 1 | P14: =+$C$22*S14*I14/1000 -> 11760 | Q14: =+P14/L14*J14 -> 392 | S14: =ROUND(D14*G14*0.00785,2) -> 1.96 | T14: =S14*H14/1000*J14 -> 0.392 | U14: =(D14+E14+F14*2)*2*H14*J14 -> 20000 | V14: Tapa incluida con perfil 50x50
A15: 12 | B15: Placa de poste 80x45x5 | C15: Pletina 80x5,0 mm. | D15: 80 | G15: 5 | H15: 45 | I15: 6000 | J15: 4 | K15: =J15*'Costo Directo'!$B$3 -> 120 | L15: =ROUNDDOWN(I15/H15,0) -> 133 | M15: =ROUNDDOWN((I15-N15)/I15,2) -> 0.99 | N15: =I15-L15*H15 -> 15 | O15: =ROUNDUP(K15/L15,0) -> 1 | P15: =+$C$22*S15*I15/1000 -> 18840 | Q15: =+P15/L15*J15 -> 566.61654 | S15: =ROUND(D15*G15*0.00785,2) -> 3.14 | T15: =S15*H15/1000*J15 -> 0.5652 | U15: =(D15+E15+F15*2)*2*H15*J15 -> 28800 | V15: Cortada de pletina
A16: 13 | B16: Placa lateral 300x100x5 | C16: Pletina 100x5,0 mm. | D16: 100 | G16: 5 | H16: 300 | I16: 6000 | J16: 4 | K16: =J16*'Costo Directo'!$B$3 -> 120 | L16: =ROUNDDOWN(I16/H16,0) -> 20 | M16: =ROUNDDOWN((I16-N16)/I16,2) -> 1 | N16: =I16-L16*H16 -> 0 | O16: =ROUNDUP(K16/L16,0) -> 6 | P16: =+$C$22*S16*I16/1000 -> 23580 | Q16: =+P16/L16*J16 -> 4716 | S16: =ROUND(D16*G16*0.00785,2) -> 3.93 | T16: =S16*H16/1000*J16 -> 4.716 | U16: =(D16+E16+F16*2)*2*H16*J16 -> 240000 | V16: Cortada de pletina
Q17: =SUM(Q4:Q16) -> 61431.045 | T17: =SUM(T4:T16) -> 59.8273 | U17: =SUM(U4:U16)/(1000*1000) -> 3.81376
A19: TABLA DE PRECIOS MP
B20: Perfil cerrado | C20: 900 | D20: $/kg
B21: Perfil cerrado e=1,5 mm. (perfil especial) | C21: 950 | D21: $/kg
B22: Pletinas - Fe liso - Perfil abierto | C22: 1000 | D22: $/kg
B23: Plancha LISA SIN PROCESAR | C23: 900 | D23: $/kg
B24: Plancha Procesada | C24: 2000 | D24: $/kg
A25: TABLA DE PRECIOS RECUBRIMIENTO
B26: Galvanizado piezas pequeñas | C26: 460 | D26: $/kg
B27: Galvanizado | C27: 460 | D27: $/kg
B28: Galvanizado especial | C28: 620 | D28: $/kg
B29: Zincado | C29: 250 | D29: $/kg
B30: Pintura Electroestática | C30: =2875/1.15*1.35 -> 3375 | D30: $/m2
B31: Pintura Electroestática piezas grandes | C31: =4025/1.15*1.35 -> 4725 | D31: $/m2
B32: Pintura especial según esp. Técnicas | C32: 7065 | D32: $/m2 | E32: Valor especial R&R actualizado a 2022-03-13
B34: Elementos reemplazados
B35: Valores x confirmar
B36: Poner atención!!

Sheet Subcontratos
A1: Subcontratos
A3: Elementos | B3: Subcontrato | C3: Unidad | D3: Consumo | E3: Precio Neto | F3: Costo | G3: OBS.
C4: de medida | D4: x Lote | E4: $/unidad | F4: x Unidad
A5: Palet Freestanding | B5: Pintura Electroestática piezas grandes | C5: [m2] | D5: =+'Materias Primas'!U17 -> 3.81376 | E5: =VLOOKUP(B5,'Materias Primas'!$B$20:$C$53,2,FALSE()) -> 4725 | F5: =E5*D5 -> 18020.016
A7: Palet Freestanding | B7: Galvanizado | C7: [kg] | D7: =+'Materias Primas'!T17 -> 59.8273 | E7: =VLOOKUP(B7,'Materias Primas'!$B$20:$C$53,2,FALSE()) -> 460 | F7: =E7*D7 -> 27520.558
A9: Palet Freestanding | B9: Soldadura | C9: [mm] | D9: =4*160+2*2*160+4*160+4*2*160+4*2*120+2*160+2*2*160+4*160+4*200+4*110+4*250+4*600 -> 10400 | E9: 1.3392857 | F9: =+E9*D9 -> 13928.571
A11: -- | B11: Maquila | C11: [kg] | F11: =+E11*D11 -> 0
A13: Palet Freestanding | B13: Transporte | C13: [unidad] | D13: =98*2 -> 196 | E13: 95000 | F13: =+E13*2/D13 -> 969.38776

Sheet Costo Directo
A1: Costo Directo de Fabricación Palet Freestanding
A3: Q= | B3: 30 | C3: Racks
B5: Acero Negro | D5: Pintura | F5: Galvanizado
B6: ($/Unidad) | C6: (%) | D6: ($/Unidad) | E6: (%) | F6: ($/Unidad) | G6: (%)
A7: Acero | B7: =+'Materias Primas'!$Q$17 -> 61431.045 | C7: =B7/B$14 -> 0.65250323 | D7: =+'Materias Primas'!$Q$17 -> 61431.045 | E7: =D7/D$14 -> 0.52155018 | F7: =+'Materias Primas'!$Q$17 -> 61431.045 | G7: =F7/F$14 -> 0.47374731
A8: Pintura/Galvanizado | B8: 0 | C8: =B8/B$14 -> 0 | D8: =+Subcontratos!F5 -> 18020.016 | E8: =D8/D$14 -> 0.15299011 | F8: =+Subcontratos!F7 -> 27520.558 | G8: =F8/F$14 -> 0.21223455
A9: Soldadura | B9: =+Subcontratos!$F$9 -> 13928.571 | C9: =B9/B$14 -> 0.14794536 | D9: =+Subcontratos!$F$9 -> 13928.571 | E9: =D9/D$14 -> 0.11825371 | F9: =+Subcontratos!$F$9 -> 13928.571 | G9: =F9/F$14 -> 0.10741512
A10: Maquila | C10: =B10/B$14 -> 0 | E10: =D10/D$14 -> 0 | G10: =F10/F$14 -> 0
A11: Mano de Obra | B11: =0.095*(B7+B10+B9+B8)*1.135/(1-0.3586)*1.12 -> 14188.851 | C11: =B11/B$14 -> 0.15070997 | D11: =0.095*(D7+D10+D9+D8)*1.135/(1-0.3586)*1.13 -> 17738.672 | E11: =D11/D$14 -> 0.1506015 | F11: =0.095*(F7+F10+F9+F8)*1.135/(1-0.3586)*1.13 -> 19543.424 | G11: =F11/F$14 -> 0.15071605
A12: Insumos | B12: =+(B7+B8+B9+B10)*1.135*0.042*1.28 -> 4598.2629 | C12: =B12/B$14 -> 0.048841451 | D12: =+(D7+D8+D9+D10)*1.135*0.042*1.28 -> 5697.8011 | E12: =D12/D$14 -> 0.048374387 | F12: =+(F7+F8+F9+F10)*1.135*0.042*1.28 -> 6277.5013 | G12: =F12/F$14 -> 0.04841118
A13: Transporte | C13: =B13/B$14 -> 0 | D13: =+Subcontratos!$F$13 -> 969.38776 | E13: =D13/D$14 -> 0.0082301116 | F13: =+Subcontratos!$F$13 -> 969.38776 | G13: =F13/F$14 -> 0.0074757778
A14: Total Costo | B14: =SUM(B7:B13) -> 94146.73 | C14: =SUM(C7:C13) -> 1 | D14: =SUM(D7:D13) -> 117785.49 | E14: =SUM(E7:E13) -> 1 | F14: =SUM(F7:F13) -> 129670.49 | G14: =SUM(G7:G13) -> 1
A15: Costo Directo | B15: =B14*1.01 -> 95088.197 | D15: =D14*1.01 -> 118963.35 | F15: =F14*1.01 -> 130967.19
A16: Peso (Kg) | B16: =+'Materias Primas'!$T$17 -> 59.8273 | D16: =+'Materias Primas'!$T$17 -> 59.8273 | F16: =+'Materias Primas'!$T$17*1.05 -> 62.818665
A17: $/Kg | B17: =B15/B16 -> 1589.378 | D17: =D15/D16 -> 1988.4459 | F17: =F15/F16 -> 2084.8452
A19: PRECIO VENTA
B21: Acero negro | D21: Pintura | F21: Galvanizado
A22: MARGEN | B22: 0.4 | D22: 0.4 | F22: 0.4
A23: PRECIO LISTA | B23: =+B15/(1-B22) -> 158480.33 | D23: =+D15/(1-D22) -> 198272.25 | F23: =+F15/(1-F22) -> 218278.65
A24: MAXIMO DESCUENTO | B24: 0.2 | D24: 0.2 | F24: 0.2
A25: PRECIO VENTA | B25: =+B23*(1-B24) -> 126784.26 | D25: =+D23*(1-D24) -> 158617.8 | F25: =+F23*(1-F24) -> 174622.92
A27: MARGEN ESPECIAL | B27: =+(B28-B15)/B28 -> 0.25 | D27: =+(D28-D15)/D28 -> 0.25 | F27: =+(F28-F15)/F28 -> 0.25
A28: PRECIO VENTA | B28: =+B25 -> 126784.26 | D28: =+D25 -> 158617.8 | F28: =+F25 -> 174622.92
H38: ,
