Workbook

Sheet Materias Primas
A1: Despiece Rack estándar 225 lts.
A2: Ítem | B2: Elementos | C2: Fierro | D2: Medidas [mm] | H2: Largo [mm] | J2: Cantidad | L2: Rendimiento | N2: Sobrante | O2: Cantidad | P2: Precio Neto | Q2: Costo | S2: Peso [kg] | U2: Superficie | V2: OBS.
D3: A | E3: B | F3: C | G3: esp. | H3: Pieza | I3: Tira | J3: x Unid. | K3: Total | L3: x Tira | N3: x Tira | O3: de Tiras | P3: $/Tira | Q3: x Unidad | S3: [kg/m] | T3: [kg] | U3: [mm²/pieza]
A4: 1 | B4: Larguero | C4: Perfil 40x40x2,0 mm. | D4: 40 | E4: 40 | G4: 2 | H4: 1130 | I4: 6000 | J4: 4 | K4: =J4*'Costo Directo'!$B$3 -> 120 | L4: =ROUNDDOWN(I4/H4,0) -> 5 | M4: =ROUNDDOWN((I4-N4)/I4,2) -> 0.94 | N4: =I4-L4*H4 -> 350 | O4: =ROUNDUP(K4/L4,0) -> 24 | P4: =+$C$13*S4*I4/1000 -> 12474 | Q4: =+P4/L4*J4 -> 9979.2 | S4: 2.31 | T4: =S4*H4/1000*J4 -> 10.4412 | U4: =(D4+E4+F4*2)*2*H4*J4 -> 723200
A5: 2 | B5: Travesaño | C5: Perfil 40x40x2,0 mm. | D5: 40 | E5: 40 | G5: 2 | H5: 700 | I5: 6000 | J5: 4 | K5: =J5*'Costo Directo'!$B$3 -> 120 | L5: =ROUNDDOWN(I5/H5,0) -> 8 | M5: =ROUNDDOWN((I5-N5)/I5,2) -> 0.93 | N5: =I5-L5*H5 -> 400 | O5: =ROUNDUP(K5/L5,0) -> 15 | P5: =+$C$13*S5*I5/1000 -> 12474 | Q5: =+P5/L5*J5 -> 6237 | S5: 2.31 | T5: =S5*H5/1000*J5 -> 6.468 | U5: =(D5+E5+F5*2)*2*H5*J5 -> 448000
A6: 3 | B6: Apoyo Interior | C6: Perfil 40x40x2,0 mm. | D6: 40 | E6: 40 | G6: 2 | H6: 170 | I6: 6000 | J6: 4 | K6: =J6*'Costo Directo'!$B$3 -> 120 | L6: =ROUNDDOWN(I6/H6,0) -> 35 | M6: =ROUNDDOWN((I6-N6)/I6,2) -> 0.99 | N6: =I6-L6*H6 -> 50 | O6: =ROUNDUP(K6/L6,0) -> 4 | P6: =+$C$13*S6*I6/1000 -> 12474 | Q6: =+P6/L6*J6 -> 1425.6 | S6: 2.31 | T6: =S6*H6/1000*J6 -> 1.5708 | U6: =(D6+E6+F6*2)*2*H6*J6 -> 108800
A7: 4 | B7: Apoyo Exterior | C7: Perfil 40x40x2,0 mm. | D7: 40 | E7: 40 | G7: 2 | H7: 250 | I7: 6000 | J7: 4 | K7: =J7*'Costo Directo'!$B$3 -> 120 | L7: =ROUNDDOWN(I7/H7,0) -> 24 | M7: =ROUNDDOWN((I7-N7)/I7,2) -> 1 | N7: =I7-L7*H7 -> 0 | O7: =ROUNDUP(K7/L7,0) -> 5 | P7: =+$C$13*S7*I7/1000 -> 12474 | Q7: =+P7/L7*J7 -> 2079 | S7: 2.31 | T7: =S7*H7/1000*J7 -> 2.31 | U7: =(D7+E7+F7*2)*2*H7*J7 -> 160000
A8: 5 | B8: Descanso Exterior | C8: Pletina 38x5,0 mm. | D8: 38 | G8: 5 | H8: 210 | I8: 6000 | J8: 8 | K8: =J8*'Costo Directo'!$B$3 -> 240 | L8: =ROUNDDOWN(I8/H8,0) -> 28 | M8: =ROUNDDOWN((I8-N8)/I8,2) -> 0.98 | N8: =I8-L8*H8 -> 120 | O8: =ROUNDUP(K8/L8,0) -> 9 | P8: =+$C$15*S8*I8/1000 -> 8940 | Q8: =+P8/L8*J8 -> 2554.2857 | S8: 1.49 | T8: =S8*H8/1000*J8 -> 2.5032 | U8: =(D8+E8+F8*2)*2*H8*J8 -> 127680
A9: 6 | B9: Descanso Interior | C9: Pletina 38x5,0 mm. | D9: 38 | G9: 5 | H9: 210 | I9: 6000 | J9: 8 | K9: =J9*'Costo Directo'!$B$3 -> 240 | L9: =ROUNDDOWN(I9/H9,0) -> 28 | M9: =ROUNDDOWN((I9-N9)/I9,2) -> 0.98 | N9: =I9-L9*H9 -> 120 | O9: =ROUNDUP(K9/L9,0) -> 9 | P9: =+$C$15*S9*I9/1000 -> 8940 | Q9: =+P9/L9*J9 -> 2554.2857 | S9: =+S8 -> 1.49 | T9: =S9*H9/1000*J9 -> 2.5032 | U9: =(D9+E9+F9*2)*2*H9*J9 -> 127680
Q10: =SUM(Q4:Q9) -> 24829.371 | T10: =SUM(T4:T9) -> 25.7964 | U10: =SUM(U4:U9)/(1000*1000) -> 1.69536
A12: TABLA DE PRECIOS MP
B13: Perfil cerrado | C13: 900 | D13: $/kg
B14: Perfil cerrado e=1,5 mm. (perfil especial) | C14: 950 | D14: $/kg
B15: Pletinas - Fe liso - Perfil abierto | C15: 1000 | D15: $/kg
B16: Plancha LISA SIN PROCESAR | C16: 900 | D16: $/kg
B17: Plancha Procesada | C17: 2000 | D17: $/kg
A18: TABLA DE PRECIOS RECUBRIMIENTO
B19: Galvanizado piezas pequeñas | C19: 460 | D19: $/kg
B20: Galvanizado | C20: 460 | D20: $/kg
B21: Galvanizado especial | C21: 620 | D21: $/kg
B22: Zincado | C22: 250 | D22: $/kg
B23: Pintura Electroestática | C23: =2875/1.15*1.35 -> 3375 | D23: $/m2
B24: Pintura Electroestática piezas grandes | C24: =4025/1.15*1.35 -> 4725 | D24: $/m2
B25: Pintura especial según esp. Técnicas | C25: 7065 | D25: $/m2 | E25: Valor especial R&R actualizado a 2022-03-13
B27: Elementos reemplazados
B28: Valores x confirmar
B29: Poner atención!!

Sheet Subcontratos
A1: Subcontratos
A3: Elementos | B3: Subcontrato | C3: Unidad | D3: Consumo | E3: Precio Neto | F3: Costo | G3: OBS.
C4: de medida | D4: x Lote | E4: $/unidad | F4: x Unidad
A5: Rack estándar 225 lts. | B5: Pintura Electroestática piezas grandes | C5: [m2] | D5: =+'Materias Primas'!U10 -> 1.69536 | E5: =VLOOKUP(B5,'Materias Primas'!$B$13:$C$46,2,FALSE) -> 4725 | F5: =E5*D5 -> 8010.576
A7: Rack estándar 225 lts. | B7: Galvanizado | C7: [kg] | D7: =+'Materias Primas'!T10 -> 25.7964 | E7: =VLOOKUP(B7,'Materias Primas'!$B$13:$C$46,2,FALSE) -> 460 | F7: =E7*D7 -> 11866.344
A9: Rack estándar 225 lts. | B9: Soldadura | C9: [mm] | D9: =40*4*12*2+40*4*2+40*2*4 -> 4480 | E9: 1.3392857 | F9: =+E9*D9 -> 6000
A11: -- | B11: Maquila | C11: [kg] | F11: =+E11*D11 -> 0
A13: Rack estándar 225 lts. | B13: Transporte | C13: [unidad] | D13: =98*2 -> 196 | E13: 95000 | F13: =+E13*2/D13 -> 969.38776

Sheet Costo Directo
A1: Costo Directo de Fabricación Rack estándar 225 lts.
A3: Q= | B3: 30 | C3: Racks
B5: Acero Negro | D5: Pintura | F5: Galvanizado
B6: ($/Unidad) | C6: (%) | D6: ($/Unidad) | E6: (%) | F6: ($/Unidad) | G6: (%)
A7: Acero | B7: =+'Materias Primas'!$Q$10 -> 24829.371 | C7: =B7/B$14 -> 0.6446656 | D7: =+'Materias Primas'!$Q$10 -> 24829.371 | E7: =D7/D$14 -> 0.5010224 | F7: =+'Materias Primas'!$Q$10 -> 24829.371 | G7: =F7/F$14 -> 0.45658259
A8: Pintura/Galvanizado | B8: 0 | C8: =B8/B$14 -> 0 | D8: =+Subcontratos!F5 -> 8010.576 | E8: =D8/D$14 -> 0.16164235 | F8: =+Subcontratos!F7 -> 11866.344 | G8: =F8/F$14 -> 0.21820794
A9: Soldadura | B9: =+Subcontratos!$F$9 -> 6000 | C9: =B9/B$14 -> 0.15578298 | D9: =+Subcontratos!$F$9 -> 6000 | E9: =D9/D$14 -> 0.12107171 | F9: =+Subcontratos!$F$9 -> 6000 | G9: =F9/F$14 -> 0.11033286
A10: Maquila | C10: =B10/B$14 -> 0 | E10: =D10/D$14 -> 0 | G10: =F10/F$14 -> 0
A11: Mano de Obra | B11: =0.095*(B7+B10+B9+B8)*1.135/(1-0.3586)*1.12 -> 5804.6121 | C11: =B11/B$14 -> 0.15070997 | D11: =0.095*(D7+D10+D9+D8)*1.135/(1-0.3586)*1.13 -> 7378.1518 | E11: =D11/D$14 -> 0.14888091 | F11: =0.095*(F7+F10+F9+F8)*1.135/(1-0.3586)*1.13 -> 8110.605 | G11: =F11/F$14 -> 0.14914437
A12: Insumos | B12: =+(B7+B8+B9+B10)*1.135*0.042*1.28 -> 1881.1343 | C12: =B12/B$14 -> 0.048841451 | D12: =+(D7+D8+D9+D10)*1.135*0.042*1.28 -> 2369.9204 | E12: =D12/D$14 -> 0.047821718 | F12: =+(F7+F8+F9+F10)*1.135*0.042*1.28 -> 2605.1901 | G12: =F12/F$14 -> 0.047906345
A13: Transporte | C13: =B13/B$14 -> 0 | D13: =+Subcontratos!$F$13 -> 969.38776 | E13: =D13/D$14 -> 0.019560905 | F13: =+Subcontratos!$F$13 -> 969.38776 | G13: =F13/F$14 -> 0.017825887
A14: Total Costo | B14: =SUM(B7:B13) -> 38515.118 | C14: =SUM(C7:C13) -> 1 | D14: =SUM(D7:D13) -> 49557.407 | E14: =SUM(E7:E13) -> 1 | F14: =SUM(F7:F13) -> 54380.898 | G14: =SUM(G7:G13) -> 1
A15: Costo Directo | B15: =B14*1.01 -> 38900.269 | D15: =D14*1.01 -> 50052.981 | F15: =F14*1.01 -> 54924.707
A16: Peso (Kg) | B16: =+'Materias Primas'!$T$10 -> 25.7964 | D16: =+'Materias Primas'!$T$10 -> 25.7964 | F16: =+'Materias Primas'!$T$10*1.05 -> 27.08622
A17: $/Kg | B17: =B15/B16 -> 1507.9728 | D17: =D15/D16 -> 1940.3088 | F17: =F15/F16 -> 2027.7731
A19: PRECIO VENTA
B21: Acero negro | D21: Pintura | F21: Galvanizado
A22: MARGEN | B22: 0.4 | D22: 0.4 | F22: 0.4
A23: PRECIO LISTA | B23: =+B15/(1-B22) -> 64833.782 | D23: =+D15/(1-D22) -> 83421.636 | F23: =+F15/(1-F22) -> 91541.179
A24: MAXIMO DESCUENTO | B24: 0.2 | D24: 0.2 | F24: 0.2
A25: PRECIO VENTA | B25: =+B23*(1-B24) -> 51867.025 | D25: =+D23*(1-D24) -> 66737.309 | F25: =+F23*(1-F24) -> 73232.943
A27: MARGEN ESPECIAL | B27: =+(B28-B15)/B28 -> 0.25 | D27: =+(D28-D15)/D28 -> 0.25 | F27: =+(F28-F15)/F28 -> 0.25
A28: PRECIO VENTA | B28: =+B25 -> 51867.025 | D28: =+D25 -> 66737.309 | F28: =+F25 -> 73232.943
H38: ,
